[
  {
    "id": "eea2dd8802784bed",
    "type": "tab",
    "label": "reset",
    "disabled": false,
    "info": "",
    "env": []
  },
  {
    "id": "2db7c7a85e956eb8",
    "type": "function",
    "z": "eea2dd8802784bed",
    "name": "function 14",
    "func": "var Request = global.get(\"Request_10\");\nvar color = \"black\";\nvar background = \"green\";\nmsg.payload = \"清\";\nif(Request.RequestID=='-'){\n    background = \"yellow\";\n}\n\nmsg.color = color;\nmsg.background = background;\n\n\nreturn msg;",
    "outputs": 1,
    "timeout": 0,
    "noerr": 0,
    "initialize": "",
    "finalize": "",
    "libs": [],
    "x": 670,
    "y": 280,
    "wires": [
      [
        "b07c4807f8337730"
      ]
    ]
  },
  {
    "id": "b07c4807f8337730",
    "type": "ui_button",
    "z": "eea2dd8802784bed",
    "name": "10清",
    "group": "7c570207316879f0",
    "order": 1,
    "width": 0,
    "height": 1,
    "passthru": false,
    "label": "10清",
    "tooltip": "",
    "color": "{{msg.color}}",
    "bgcolor": "{{msg.background}}",
    "className": "",
    "icon": "",
    "payload": "",
    "payloadType": "str",
    "topic": "topic",
    "topicType": "msg",
    "x": 820,
    "y": 280,
    "wires": [
      [
        "36c042cb48b4f516"
      ]
    ]
  },
  {
    "id": "62b5e4b25fd6a165",
    "type": "function",
    "z": "eea2dd8802784bed",
    "name": "function 16",
    "func": "var Request = global.get(\"Request_20\");\nvar color = \"black\";\nvar background = \"green\";\nmsg.payload = \"清\";\nif(Request.RequestID=='-'){\n    background = \"yellow\";\n}\n\nmsg.color = color;\nmsg.background = background;\n\n\nreturn msg;",
    "outputs": 1,
    "timeout": 0,
    "noerr": 0,
    "initialize": "",
    "finalize": "",
    "libs": [],
    "x": 670,
    "y": 320,
    "wires": [
      [
        "b8a8b3d1fd0fa4ab"
      ]
    ]
  },
  {
    "id": "b8a8b3d1fd0fa4ab",
    "type": "ui_button",
    "z": "eea2dd8802784bed",
    "name": "20清",
    "group": "7c570207316879f0",
    "order": 2,
    "width": 0,
    "height": 1,
    "passthru": false,
    "label": "20清",
    "tooltip": "",
    "color": "{{msg.color}}",
    "bgcolor": "{{msg.background}}",
    "className": "",
    "icon": "",
    "payload": "",
    "payloadType": "str",
    "topic": "topic",
    "topicType": "msg",
    "x": 820,
    "y": 320,
    "wires": [
      [
        "9f34663d93ab1ab2"
      ]
    ]
  },
  {
    "id": "617f12b9ef2a5e65",
    "type": "function",
    "z": "eea2dd8802784bed",
    "name": "function 17",
    "func": "var Request = global.get(\"Request_30\");\nvar color = \"black\";\nvar background = \"green\";\nmsg.payload = \"清\";\nif(Request.RequestID=='-'){\n    background = \"yellow\";\n}\n\nmsg.color = color;\nmsg.background = background;\n\n\nreturn msg;",
    "outputs": 1,
    "timeout": 0,
    "noerr": 0,
    "initialize": "",
    "finalize": "",
    "libs": [],
    "x": 670,
    "y": 360,
    "wires": [
      [
        "b1c8da5b26fe42b9"
      ]
    ]
  },
  {
    "id": "b1c8da5b26fe42b9",
    "type": "ui_button",
    "z": "eea2dd8802784bed",
    "name": "30清",
    "group": "7c570207316879f0",
    "order": 3,
    "width": 0,
    "height": 1,
    "passthru": false,
    "label": "30清",
    "tooltip": "",
    "color": "{{msg.color}}",
    "bgcolor": "{{msg.background}}",
    "className": "",
    "icon": "",
    "payload": "",
    "payloadType": "str",
    "topic": "topic",
    "topicType": "msg",
    "x": 820,
    "y": 360,
    "wires": [
      [
        "fa486fd304725656"
      ]
    ]
  },
  {
    "id": "8f4f828da2c809eb",
    "type": "function",
    "z": "eea2dd8802784bed",
    "name": "function 18",
    "func": "var Request = global.get(\"Request_40\");\nvar color = \"black\";\nvar background = \"green\";\nmsg.payload = \"清\";\nif(Request.RequestID=='-'){\n    background = \"yellow\";\n}\n\nmsg.color = color;\nmsg.background = background;\n\n\nreturn msg;",
    "outputs": 1,
    "timeout": 0,
    "noerr": 0,
    "initialize": "",
    "finalize": "",
    "libs": [],
    "x": 670,
    "y": 400,
    "wires": [
      [
        "80430398ff1caa07"
      ]
    ]
  },
  {
    "id": "80430398ff1caa07",
    "type": "ui_button",
    "z": "eea2dd8802784bed",
    "name": "40清",
    "group": "7c570207316879f0",
    "order": 4,
    "width": 0,
    "height": 1,
    "passthru": false,
    "label": "40清",
    "tooltip": "",
    "color": "{{msg.color}}",
    "bgcolor": "{{msg.background}}",
    "className": "",
    "icon": "",
    "payload": "",
    "payloadType": "str",
    "topic": "topic",
    "topicType": "msg",
    "x": 820,
    "y": 400,
    "wires": [
      [
        "b775fa9adcc86037"
      ]
    ]
  },
  {
    "id": "58a3f7b87851661e",
    "type": "function",
    "z": "eea2dd8802784bed",
    "name": "function 19",
    "func": "var Request = global.get(\"Request_50\");\nvar color = \"black\";\nvar background = \"green\";\nmsg.payload = \"清\";\nif(Request.RequestID=='-'){\n    background = \"yellow\";\n}\n\nmsg.color = color;\nmsg.background = background;\n\n\nreturn msg;",
    "outputs": 1,
    "timeout": 0,
    "noerr": 0,
    "initialize": "",
    "finalize": "",
    "libs": [],
    "x": 670,
    "y": 500,
    "wires": [
      [
        "38f6ce7b87f617a5"
      ]
    ]
  },
  {
    "id": "38f6ce7b87f617a5",
    "type": "ui_button",
    "z": "eea2dd8802784bed",
    "name": "50清",
    "group": "7c570207316879f0",
    "order": 5,
    "width": 0,
    "height": 1,
    "passthru": false,
    "label": "50清",
    "tooltip": "",
    "color": "{{msg.color}}",
    "bgcolor": "{{msg.background}}",
    "className": "",
    "icon": "",
    "payload": "",
    "payloadType": "str",
    "topic": "topic",
    "topicType": "msg",
    "x": 820,
    "y": 500,
    "wires": [
      [
        "da381d60b50c97af"
      ]
    ]
  },
  {
    "id": "090c77b0a1acc9f2",
    "type": "function",
    "z": "eea2dd8802784bed",
    "name": "function 20",
    "func": "var Request = global.get(\"Request_60\");\nvar color = \"black\";\nvar background = \"green\";\nmsg.payload = \"清\";\nif(Request.RequestID=='-'){\n    background = \"yellow\";\n}\n\nmsg.color = color;\nmsg.background = background;\n\n\nreturn msg;",
    "outputs": 1,
    "timeout": 0,
    "noerr": 0,
    "initialize": "",
    "finalize": "",
    "libs": [],
    "x": 670,
    "y": 540,
    "wires": [
      [
        "f3fc331c791b0a69"
      ]
    ]
  },
  {
    "id": "f3fc331c791b0a69",
    "type": "ui_button",
    "z": "eea2dd8802784bed",
    "name": "60清",
    "group": "7c570207316879f0",
    "order": 6,
    "width": 0,
    "height": 1,
    "passthru": false,
    "label": "60清",
    "tooltip": "",
    "color": "{{msg.color}}",
    "bgcolor": "{{msg.background}}",
    "className": "",
    "icon": "",
    "payload": "",
    "payloadType": "str",
    "topic": "topic",
    "topicType": "msg",
    "x": 820,
    "y": 540,
    "wires": [
      [
        "132f5637a0924f21"
      ]
    ]
  },
  {
    "id": "2c3082079261633f",
    "type": "function",
    "z": "eea2dd8802784bed",
    "name": "function 21",
    "func": "var Request = global.get(\"Request_70\");\nvar color = \"black\";\nvar background = \"green\";\nmsg.payload = \"清\";\nif(Request.RequestID=='-'){\n    background = \"yellow\";\n}\n\nmsg.color = color;\nmsg.background = background;\n\n\nreturn msg;",
    "outputs": 1,
    "timeout": 0,
    "noerr": 0,
    "initialize": "",
    "finalize": "",
    "libs": [],
    "x": 670,
    "y": 580,
    "wires": [
      [
        "d8d7488e1b5b10c8"
      ]
    ]
  },
  {
    "id": "d8d7488e1b5b10c8",
    "type": "ui_button",
    "z": "eea2dd8802784bed",
    "name": "70清",
    "group": "7c570207316879f0",
    "order": 7,
    "width": 0,
    "height": 1,
    "passthru": false,
    "label": "70清",
    "tooltip": "",
    "color": "{{msg.color}}",
    "bgcolor": "{{msg.background}}",
    "className": "",
    "icon": "",
    "payload": "",
    "payloadType": "str",
    "topic": "topic",
    "topicType": "msg",
    "x": 820,
    "y": 580,
    "wires": [
      [
        "4ecb2d593706c430"
      ]
    ]
  },
  {
    "id": "8d167910954787f7",
    "type": "function",
    "z": "eea2dd8802784bed",
    "name": "function 22",
    "func": "var Request = global.get(\"Request_80\");\nvar color = \"black\";\nvar background = \"green\";\nmsg.payload = \"清\";\nif(Request.RequestID=='-'){\n    background = \"yellow\";\n}\n\nmsg.color = color;\nmsg.background = background;\n\n\nreturn msg;",
    "outputs": 1,
    "timeout": 0,
    "noerr": 0,
    "initialize": "",
    "finalize": "",
    "libs": [],
    "x": 670,
    "y": 620,
    "wires": [
      [
        "ce92259995916181"
      ]
    ]
  },
  {
    "id": "ce92259995916181",
    "type": "ui_button",
    "z": "eea2dd8802784bed",
    "name": "80清",
    "group": "7c570207316879f0",
    "order": 8,
    "width": 0,
    "height": 1,
    "passthru": false,
    "label": "80清",
    "tooltip": "",
    "color": "{{msg.color}}",
    "bgcolor": "{{msg.background}}",
    "className": "",
    "icon": "",
    "payload": "",
    "payloadType": "str",
    "topic": "topic",
    "topicType": "msg",
    "x": 820,
    "y": 620,
    "wires": [
      [
        "23da0fcb2c6f2e11"
      ]
    ]
  },
  {
    "id": "2e7b27cac7f0b81f",
    "type": "function",
    "z": "eea2dd8802784bed",
    "name": "function 23",
    "func": "var Request = global.get(\"Request_90\");\nvar color = \"black\";\nvar background = \"green\";\nmsg.payload = \"清\";\nif(Request.RequestID=='-'){\n    background = \"yellow\";\n}\n\nmsg.color = color;\nmsg.background = background;\n\n\nreturn msg;",
    "outputs": 1,
    "timeout": 0,
    "noerr": 0,
    "initialize": "",
    "finalize": "",
    "libs": [],
    "x": 670,
    "y": 660,
    "wires": [
      [
        "f03a2bcf2f7a33fd"
      ]
    ]
  },
  {
    "id": "f03a2bcf2f7a33fd",
    "type": "ui_button",
    "z": "eea2dd8802784bed",
    "name": "90清",
    "group": "7c570207316879f0",
    "order": 9,
    "width": 0,
    "height": 1,
    "passthru": false,
    "label": "90清",
    "tooltip": "",
    "color": "{{msg.color}}",
    "bgcolor": "{{msg.background}}",
    "className": "",
    "icon": "",
    "payload": "",
    "payloadType": "str",
    "topic": "topic",
    "topicType": "msg",
    "x": 820,
    "y": 660,
    "wires": [
      [
        "3cd932a42f9f4975"
      ]
    ]
  },
  {
    "id": "de9de887d62442e6",
    "type": "function",
    "z": "eea2dd8802784bed",
    "name": "function 24",
    "func": "var Request = global.get(\"Request_100\");\nvar color = \"black\";\nvar background = \"green\";\n\nif(Request.RequestID=='-'){\n    background = \"yellow\";\n}\n\nmsg.color = color;\nmsg.background = background;\n\n\nreturn msg;",
    "outputs": 1,
    "timeout": 0,
    "noerr": 0,
    "initialize": "",
    "finalize": "",
    "libs": [],
    "x": 670,
    "y": 700,
    "wires": [
      [
        "3417ab2b7420517c"
      ]
    ]
  },
  {
    "id": "3417ab2b7420517c",
    "type": "ui_button",
    "z": "eea2dd8802784bed",
    "name": "100清",
    "group": "7c570207316879f0",
    "order": 10,
    "width": 0,
    "height": 1,
    "passthru": false,
    "label": "100清",
    "tooltip": "",
    "color": "{{msg.color}}",
    "bgcolor": "{{msg.background}}",
    "className": "",
    "icon": "",
    "payload": "",
    "payloadType": "str",
    "topic": "topic",
    "topicType": "msg",
    "x": 820,
    "y": 700,
    "wires": [
      [
        "18ba074deb46a67c"
      ]
    ]
  },
  {
    "id": "36c042cb48b4f516",
    "type": "http request",
    "z": "eea2dd8802784bed",
    "name": "",
    "method": "GET",
    "ret": "txt",
    "paytoqs": "ignore",
    "url": "http://192.168.110.10:1880/10/RequestID",
    "tls": "",
    "persist": false,
    "proxy": "",
    "insecureHTTPParser": false,
    "authType": "",
    "senderr": false,
    "headers": [],
    "x": 960,
    "y": 280,
    "wires": [
      [
        "dbf52271522acd39"
      ]
    ]
  },
  {
    "id": "dbf52271522acd39",
    "type": "debug",
    "z": "eea2dd8802784bed",
    "name": "debug 23",
    "active": true,
    "tosidebar": true,
    "console": false,
    "tostatus": false,
    "complete": "false",
    "statusVal": "",
    "statusType": "auto",
    "x": 1120,
    "y": 280,
    "wires": []
  },
  {
    "id": "9f34663d93ab1ab2",
    "type": "http request",
    "z": "eea2dd8802784bed",
    "name": "",
    "method": "GET",
    "ret": "txt",
    "paytoqs": "ignore",
    "url": "http://192.168.110.20:1880/20/RequestID",
    "tls": "",
    "persist": false,
    "proxy": "",
    "insecureHTTPParser": false,
    "authType": "",
    "senderr": false,
    "headers": [],
    "x": 960,
    "y": 320,
    "wires": [
      [
        "c60bf11d052e6b9c"
      ]
    ]
  },
  {
    "id": "c60bf11d052e6b9c",
    "type": "debug",
    "z": "eea2dd8802784bed",
    "name": "debug 24",
    "active": true,
    "tosidebar": true,
    "console": false,
    "tostatus": false,
    "complete": "false",
    "statusVal": "",
    "statusType": "auto",
    "x": 1120,
    "y": 320,
    "wires": []
  },
  {
    "id": "fa486fd304725656",
    "type": "http request",
    "z": "eea2dd8802784bed",
    "name": "",
    "method": "GET",
    "ret": "txt",
    "paytoqs": "ignore",
    "url": "http://192.168.110.20:1880/30/RequestID",
    "tls": "",
    "persist": false,
    "proxy": "",
    "insecureHTTPParser": false,
    "authType": "",
    "senderr": false,
    "headers": [],
    "x": 960,
    "y": 360,
    "wires": [
      [
        "94d2a800ebe270f7"
      ]
    ]
  },
  {
    "id": "94d2a800ebe270f7",
    "type": "debug",
    "z": "eea2dd8802784bed",
    "name": "debug 25",
    "active": true,
    "tosidebar": true,
    "console": false,
    "tostatus": false,
    "complete": "false",
    "statusVal": "",
    "statusType": "auto",
    "x": 1120,
    "y": 360,
    "wires": []
  },
  {
    "id": "b775fa9adcc86037",
    "type": "http request",
    "z": "eea2dd8802784bed",
    "name": "",
    "method": "GET",
    "ret": "txt",
    "paytoqs": "ignore",
    "url": "http://192.168.110.40:1880/40/RequestID",
    "tls": "",
    "persist": false,
    "proxy": "",
    "insecureHTTPParser": false,
    "authType": "",
    "senderr": false,
    "headers": [],
    "x": 960,
    "y": 400,
    "wires": [
      [
        "e4333cebb87d3043"
      ]
    ]
  },
  {
    "id": "e4333cebb87d3043",
    "type": "debug",
    "z": "eea2dd8802784bed",
    "name": "debug 26",
    "active": true,
    "tosidebar": true,
    "console": false,
    "tostatus": false,
    "complete": "false",
    "statusVal": "",
    "statusType": "auto",
    "x": 1120,
    "y": 400,
    "wires": []
  },
  {
    "id": "da381d60b50c97af",
    "type": "http request",
    "z": "eea2dd8802784bed",
    "name": "",
    "method": "GET",
    "ret": "txt",
    "paytoqs": "ignore",
    "url": "http://192.168.110.50:1880/50/RequestID",
    "tls": "",
    "persist": false,
    "proxy": "",
    "insecureHTTPParser": false,
    "authType": "",
    "senderr": false,
    "headers": [],
    "x": 960,
    "y": 500,
    "wires": [
      [
        "a6e6a13617791ab0"
      ]
    ]
  },
  {
    "id": "a6e6a13617791ab0",
    "type": "debug",
    "z": "eea2dd8802784bed",
    "name": "debug 27",
    "active": true,
    "tosidebar": true,
    "console": false,
    "tostatus": false,
    "complete": "false",
    "statusVal": "",
    "statusType": "auto",
    "x": 1120,
    "y": 500,
    "wires": []
  },
  {
    "id": "132f5637a0924f21",
    "type": "http request",
    "z": "eea2dd8802784bed",
    "name": "",
    "method": "GET",
    "ret": "txt",
    "paytoqs": "ignore",
    "url": "http://192.168.110.60:1880/60/RequestID",
    "tls": "",
    "persist": false,
    "proxy": "",
    "insecureHTTPParser": false,
    "authType": "",
    "senderr": false,
    "headers": [],
    "x": 960,
    "y": 540,
    "wires": [
      [
        "d2bb67edd31c4231"
      ]
    ]
  },
  {
    "id": "d2bb67edd31c4231",
    "type": "debug",
    "z": "eea2dd8802784bed",
    "name": "debug 28",
    "active": true,
    "tosidebar": true,
    "console": false,
    "tostatus": false,
    "complete": "false",
    "statusVal": "",
    "statusType": "auto",
    "x": 1120,
    "y": 540,
    "wires": []
  },
  {
    "id": "4ecb2d593706c430",
    "type": "http request",
    "z": "eea2dd8802784bed",
    "name": "",
    "method": "GET",
    "ret": "txt",
    "paytoqs": "ignore",
    "url": "http://192.168.110.70:1880/70/RequestID",
    "tls": "",
    "persist": false,
    "proxy": "",
    "insecureHTTPParser": false,
    "authType": "",
    "senderr": false,
    "headers": [],
    "x": 960,
    "y": 580,
    "wires": [
      [
        "37fbc0ebcdd83062"
      ]
    ]
  },
  {
    "id": "37fbc0ebcdd83062",
    "type": "debug",
    "z": "eea2dd8802784bed",
    "name": "debug 29",
    "active": true,
    "tosidebar": true,
    "console": false,
    "tostatus": false,
    "complete": "false",
    "statusVal": "",
    "statusType": "auto",
    "x": 1120,
    "y": 580,
    "wires": []
  },
  {
    "id": "23da0fcb2c6f2e11",
    "type": "http request",
    "z": "eea2dd8802784bed",
    "name": "",
    "method": "GET",
    "ret": "txt",
    "paytoqs": "ignore",
    "url": "http://192.168.110.80:1880/80/RequestID",
    "tls": "",
    "persist": false,
    "proxy": "",
    "insecureHTTPParser": false,
    "authType": "",
    "senderr": false,
    "headers": [],
    "x": 960,
    "y": 620,
    "wires": [
      [
        "3bcff78ccf5b9002"
      ]
    ]
  },
  {
    "id": "3bcff78ccf5b9002",
    "type": "debug",
    "z": "eea2dd8802784bed",
    "name": "debug 30",
    "active": true,
    "tosidebar": true,
    "console": false,
    "tostatus": false,
    "complete": "false",
    "statusVal": "",
    "statusType": "auto",
    "x": 1120,
    "y": 620,
    "wires": []
  },
  {
    "id": "3cd932a42f9f4975",
    "type": "http request",
    "z": "eea2dd8802784bed",
    "name": "",
    "method": "GET",
    "ret": "txt",
    "paytoqs": "ignore",
    "url": "http://192.168.110.90:1880/90/RequestID",
    "tls": "",
    "persist": false,
    "proxy": "",
    "insecureHTTPParser": false,
    "authType": "",
    "senderr": false,
    "headers": [],
    "x": 960,
    "y": 660,
    "wires": [
      [
        "a15a01907168297c"
      ]
    ]
  },
  {
    "id": "a15a01907168297c",
    "type": "debug",
    "z": "eea2dd8802784bed",
    "name": "debug 31",
    "active": true,
    "tosidebar": true,
    "console": false,
    "tostatus": false,
    "complete": "false",
    "statusVal": "",
    "statusType": "auto",
    "x": 1120,
    "y": 660,
    "wires": []
  },
  {
    "id": "18ba074deb46a67c",
    "type": "http request",
    "z": "eea2dd8802784bed",
    "name": "",
    "method": "GET",
    "ret": "txt",
    "paytoqs": "ignore",
    "url": "http://192.168.110.100:1880/100/RequestID",
    "tls": "",
    "persist": false,
    "proxy": "",
    "insecureHTTPParser": false,
    "authType": "",
    "senderr": false,
    "headers": [],
    "x": 960,
    "y": 700,
    "wires": [
      [
        "69bcb2eaad3be106"
      ]
    ]
  },
  {
    "id": "69bcb2eaad3be106",
    "type": "debug",
    "z": "eea2dd8802784bed",
    "name": "debug 32",
    "active": true,
    "tosidebar": true,
    "console": false,
    "tostatus": false,
    "complete": "false",
    "statusVal": "",
    "statusType": "auto",
    "x": 1120,
    "y": 700,
    "wires": []
  },
  {
    "id": "b7e924aa131096aa",
    "type": "function",
    "z": "eea2dd8802784bed",
    "name": "function 15",
    "func": "\nreturn msg;",
    "outputs": 1,
    "timeout": 0,
    "noerr": 0,
    "initialize": "",
    "finalize": "",
    "libs": [],
    "x": 465,
    "y": 280,
    "wires": [
      [
        "2db7c7a85e956eb8",
        "62b5e4b25fd6a165",
        "617f12b9ef2a5e65",
        "58a3f7b87851661e",
        "8f4f828da2c809eb",
        "090c77b0a1acc9f2",
        "2c3082079261633f",
        "2e7b27cac7f0b81f",
        "de9de887d62442e6",
        "8d167910954787f7",
        "031f8a777dfccc4a"
      ]
    ],
    "l": false
  },
  {
    "id": "4e465b63caf14270",
    "type": "link in",
    "z": "eea2dd8802784bed",
    "name": "RESET",
    "links": [
      "a60c3a900faa30dd"
    ],
    "x": 325,
    "y": 280,
    "wires": [
      [
        "b7e924aa131096aa"
      ]
    ]
  },
  {
    "id": "031f8a777dfccc4a",
    "type": "function",
    "z": "eea2dd8802784bed",
    "name": "function 108",
    "func": "var Request = global.get(\"Request_41\");\nvar color = \"black\";\nvar background = \"green\";\nmsg.payload = \"清\";\nif(Request.RequestID=='-'){\n    background = \"yellow\";\n}\n\nmsg.color = color;\nmsg.background = background;\n\n\nreturn msg;",
    "outputs": 1,
    "timeout": 0,
    "noerr": 0,
    "initialize": "",
    "finalize": "",
    "libs": [],
    "x": 670,
    "y": 440,
    "wires": [
      [
        "2f8949fce481207f"
      ]
    ]
  },
  {
    "id": "2f8949fce481207f",
    "type": "ui_button",
    "z": "eea2dd8802784bed",
    "name": "41清",
    "group": "7c570207316879f0",
    "order": 4,
    "width": 0,
    "height": 1,
    "passthru": false,
    "label": "41清",
    "tooltip": "",
    "color": "{{msg.color}}",
    "bgcolor": "{{msg.background}}",
    "className": "",
    "icon": "",
    "payload": "",
    "payloadType": "str",
    "topic": "topic",
    "topicType": "msg",
    "x": 820,
    "y": 440,
    "wires": [
      [
        "720fbb7c9262fda4"
      ]
    ]
  },
  {
    "id": "720fbb7c9262fda4",
    "type": "http request",
    "z": "eea2dd8802784bed",
    "name": "",
    "method": "GET",
    "ret": "txt",
    "paytoqs": "ignore",
    "url": "http://192.168.110.40:1880/41/RequestID",
    "tls": "",
    "persist": false,
    "proxy": "",
    "insecureHTTPParser": false,
    "authType": "",
    "senderr": false,
    "headers": [],
    "x": 960,
    "y": 440,
    "wires": [
      [
        "46ee504ad040c4a5"
      ]
    ]
  },
  {
    "id": "46ee504ad040c4a5",
    "type": "debug",
    "z": "eea2dd8802784bed",
    "name": "debug 35",
    "active": true,
    "tosidebar": true,
    "console": false,
    "tostatus": false,
    "complete": "false",
    "statusVal": "",
    "statusType": "auto",
    "x": 1120,
    "y": 440,
    "wires": []
  }
]